{
  "$schema": "../node_modules/@angular-devkit/schematics/collection-schema.json",
  "schematics": {
    "element": {
      "description": "ng-joint shape element schematics",
      "factory": "./ng-joint-schematics/shape/index#ngJointElementSchematics",
      "schema": "./schemas/ng-joint-shape-schema.json"
    },
    "link": {
      "description": "ng-joint shape link schematics",
      "factory": "./ng-joint-schematics/shape/index#ngJointLinkSchematics",
      "schema": "./schemas/ng-joint-shape-schema.json"
    },
    "lib": {
      "description": "ng-joint shape library schematics",
      "factory": "./ng-joint-schematics/lib/index#ngJointLibSchematics",
      "schema": "./schemas/ng-joint-lib-schema.json"
    }
  }
}
